wikichangewatcher/__init__.py
wikichangewatcher/__main__.py
wikichangewatcher/cli.py
wikichangewatcher/wikichangewatcher.py
wikichangewatcher-1.1.1.dist-info/LICENSE
wikichangewatcher-1.1.1.dist-info/METADATA
wikichangewatcher-1.1.1.dist-info/WHEEL
wikichangewatcher-1.1.1.dist-info/entry_points.txt
wikichangewatcher-1.1.1.dist-info/top_level.txt
wikichangewatcher-1.1.1.dist-info/RECORD
