Metadata-Version: 2.1
Name: wikichangewatcher
Version: 1.1.1
Summary: Real-time monitoring/filtering of global Wikipedia page edits
Home-page: http://github.com/eriknyquist/wikichangewatcher
Author: Erik Nyquist
Author-email: eknyquist@gmail.com
License: Apache 2.0
Classifier: Development Status :: 5 - Production/Stable
Classifier: Intended Audience :: Developers
Classifier: Intended Audience :: Science/Research
Classifier: Intended Audience :: Education
Classifier: Intended Audience :: Information Technology
Classifier: License :: OSI Approved :: MIT License
Classifier: Programming Language :: Python :: 3.9
Classifier: Programming Language :: Python :: 3.10
Classifier: Programming Language :: Python :: 3.11
Requires-Python: >=3.9
License-File: LICENSE
Requires-Dist: sseclient
